davidkhala/gcp/auth/__init__.py
davidkhala/gcp/auth/api_key.py
davidkhala/gcp/auth/ci.py
davidkhala/gcp/auth/service_account.py
davidkhala/gcp/core/__init__.py
davidkhala_gcp-0.4.2.dist-info/METADATA
davidkhala_gcp-0.4.2.dist-info/WHEEL
davidkhala_gcp-0.4.2.dist-info/RECORD
